nitdms/__init__.py
nitdms/common.py
nitdms/daqmx_scalers.py
nitdms/exceptions.py
nitdms/reader.py
nitdms/tdsapi.py
nitdms/version.py
waveformDT/__init__.py
waveformDT/test_wdt.py
waveformDT/waveform.py
nitdms-2.0.7.dist-info/LICENSE
nitdms-2.0.7.dist-info/METADATA
nitdms-2.0.7.dist-info/WHEEL
nitdms-2.0.7.dist-info/top_level.txt
nitdms-2.0.7.dist-info/RECORD
