Metadata-Version: 2.1
Name: nitdms
Version: 2.0.7
Summary: A pythonic reader for TDMS files generated by LabVIEW
Home-page: https://github.com/l-johnston/nitdms
Author: Lee Johnston
Author-email: lee.johnston.100@gmail.com
License: MIT
Platform: UNKNOWN
Classifier: Programming Language :: Python :: 3
Classifier: Topic :: Scientific/Engineering
Classifier: License :: OSI Approved :: MIT License
Classifier: Intended Audience :: Science/Research
Classifier: Natural Language :: English
Requires-Dist: numpy
Requires-Dist: matplotlib
Requires-Dist: unyt
